[
  {
    "id": "1773784935265",
    "title": "Lead Scores вЂ” 17 Mar 2026",
    "content": "*рџЋЇ Lead Score Update*\n\nScored 4 ICPs вЂ” 0 hot, 0 warm, 4 cold\n\n\n_Full scores updated in dashboard в†’ ICP tab_",
    "type": "lead-score",
    "createdAt": "2026-03-17T22:02:15.265Z"
  },
  {
    "id": "1773778315344",
    "title": "Daily Briefing вЂ” Tuesday 17 March 2026",
    "content": "Morning Briefing вЂ” Tuesday 17 March 2026\n\nTODAY'S CALENDAR (Europe/London)\nвљ пёЏ SCHEDULE CLASH: DDAS (12:00вЂ“13:00) overlaps Gym/Focus (11:30вЂ“13:30)\nвЂў 11:30 AM вЂ“ 1:30 PM: Gym / Focus вљ пёЏ Overlaps DDAS\nвЂў 12:00 PM вЂ“ 1:00 PM: DDAS вљ пёЏ Check priority vs gym\nвЂў 4:00 PM вЂ“ 4:30 PM: Matthew / Raymond\nвЂў 6:00 PM вЂ“ 7:00 PM: Apply to Jobs\n\nTOMORROW (Wed 18 March)\nвЂў 8:00 AM вЂ“ 9:00 AM: Bills\nвЂў 11:30 AM вЂ“ 1:30 PM: Gym / Focus\nвЂў 4:00 PM вЂ“ 5:00 PM: Gym / Focus (check вЂ” two gym blocks?)\n\nOPEN THREADS\n- Conversational AI campaigns вЂ” NOT LIVE (overdue)\n- Apollo tasks вЂ” mark all done\n- Talent Flow contacts в†’ Nth Layer sequence\n- LinkedIn follow-ups from Easy Apply (9 submissions this week)\n- Chase outstanding debts\n- SEO audit on sonesse.ai + nthlayer.co.uk (TODO from 16th)\n- Programmatic SEO for Sonesse (TODO from 16th)\n- Proxycurl signup (nubela.co/proxycurl) for LinkedIn monitoring\n- Apollo lists for LinkedIn monitoring вЂ” which lists? (unanswered)\n- VC firms sheet (499 firms) вЂ” next step?\n\nAGENTS TODAY\nвњ… 6:30 AM вЂ“ Daily reminders\nвњ… 8:00 AM вЂ“ Job agent + email parser\nвњ… 8:30 AM вЂ“ This briefing\nрџ”ґ 5:00 PM вЂ“ Sales Pulse BROKEN (auth 401)\nрџ”ґ 6:00 PM вЂ“ British TV Tonight BROKEN (delivery error)\nвњ… 9:00 PM вЂ“ Debrief reminder + email\nвњ… 11:00 PM вЂ“ Backup\n\nLIVE & WORKING\nGoG/Gmail, Google Calendar, Apollo API, Dashboard (Cloudflare), n8n, Job agent, Community monitor, Camoufox + Chrome CDP (LinkedIn), Whisper, VC firms sheet\n\nNEEDS YOUR ACTION\n- Brave Search API key\n- Pipedrive API key (Settings в†’ Personal Preferences в†’ API)\n- nthlayerbot.co.uk в†’ Cloudflare nameservers\n- Proxycurl signup\n- Apollo lists for LinkedIn monitoring\n- Fix Sales Pulse + TV agents (say the word)\n- Pricing for Sonesse + Nth Layer still undefined\n\nQ1 GOALS\n- Sonesse: 10 hot leads вЂ” community monitor running, campaigns not yet live\n- Nth Layer: 1 deal closed вЂ” 499 VC firms in sheet, Talent Flow contacts not moved yet\n\nONE THING TODAY: Get conversational AI campaigns live вЂ” it is the #1 lead gen lever for Sonesse and has been open too long.",
    "type": "daily",
    "createdAt": "2026-03-17T20:11:55.000Z"
  },
  {
    "id": "1773736310973",
    "title": "Daily Briefing вЂ” Tuesday 17 March 2026",
    "content": "Morning Briefing вЂ” Tuesday 17 March 2026\n\nTODAY'S CALENDAR:\n- 11:30вЂ“13:30: Gym/Focus\n- 12:00вЂ“13:00: DDAS (вљ пёЏ overlaps with Gym block)\n- 14:00вЂ“14:30: QC call вЂ” Matthew & Daniel Gwalter (prep needed)\n- 16:00вЂ“16:30: Matthew / Raymond\n- 16:00вЂ“17:00: Gym/Focus (вљ пёЏ overlaps with Raymond call)\n\nTOMORROW (Wed 18 March): Gym/Focus 11:30 and 16:00, otherwise clear.\n\nOPEN THREADS:\n- LinkedIn Automation: WSL shutdown done today, Chrome CDP live, run once this morning only\n- Apollo Lead Gen Cron: built and ready, awaiting approval to activate\n- Sonesse Pricing: still undefined вЂ” blocks sales motion on both ventures\n- Andy Jones meeting: calendar invite still pending (need his email)\n- VC Investor Sheet: 499 firms scraped (2026-03-16), needs review/next step\n- Sonesse SEO Tutorials: daily cron running 9AM weekdays\n- Daily Briefing/Debrief crons: previous Slack target errors, monitoring\n\nAGENTS TODAY:\n6:30AM Daily Reminders, 8AM Job Agent + Community Monitor, 8:30AM This Briefing, 9AM Sonesse SEO Tutorial, 11AM Recipes, 5PM Sales Pulse, 6PM TV Guide, 7PM Evening Recipe, 8PM Debrief Reminder, 9PM Debrief email, 11PM Backup + Pruner, 11:55PM Daily Summary\n\nLIVE & WORKING:\nGoG/Gmail, Apollo API, Dashboard (Cloudflare), Google Calendar, LinkedIn Chrome CDP, n8n, Whisper, All daily crons\n\nSTILL NEEDS ACTION:\n- Brave Search API key\n- Pipedrive API key\n- nthlayerbot.co.uk nameservers в†’ Cloudflare\n- Google Sheet ID for community tracker\n- Andy Jones email\n- Sonesse + Nth Layer pricing defined\n- Approve Apollo lead gen cron\n\nQ1 GOALS:\n- Sonesse: 10 hot leads вЂ” Apollo cron ready to activate\n- Nth Layer: 1 deal closed вЂ” QC call today 2pm with Daniel Gwalter\n\nONE THING TODAY:\nPrep for 2pm QC call with Daniel Gwalter (potential Nth Layer close). Approve Apollo lead gen cron. Two actions, both Q1 goals move forward.",
    "type": "daily",
    "createdAt": "2026-03-17T08:31:50.000Z"
  },
  {
    "id": "1773231196169",
    "title": "Daily Briefing вЂ” Wednesday 11 March 2026",
    "content": "OpenClaw Daily Briefing вЂ” Wednesday 11 March 2026 (12:10 UTC)\n\nвњ… LIVE & WORKING\n- GoG/Gmail, Apollo API, Cloudflare Tunnel, Dashboard (DNS pending)\n- 7AM Workout, 8:30AM Briefing, 9PM Debrief, 11PM Backup вЂ” all firing\n- Pipedrive key confirmed in memory (agent not yet built)\n- Shell/Exec access full, Readwise API 130 highlights\n\nрџ”„ IN PROGRESS\n- Apollo lead gen agent (9AM) вЂ” all keys ready, BUILD NEEDED TODAY\n- Recipe agent, Readwise knowledge graph, Community tracker, Job agent, Meta-agent, Open questions agent\n\nвЏі PENDING YOUR ACTION\n- Brave Search API key (api.search.brave.com вЂ” 5 min task)\n- DNS nameservers в†’ point dashboard.nthlayerbot.co.uk to Cloudflare\n- Google Sheet ID for community tracker\n- Podcast list for Whisper agent\n\nрџ”’ BLOCKED\n- LinkedIn automation: wsl --shutdown from PowerShell в†’ relaunch в†’ test curl localhost:9222\n\nрџ“€ GOAL PROGRESS (Q1 вЂ” 21 days left)\n- Sonesse hot leads: 0 / 10 рџ”ґ\n- Nth Layer deal: 0 / 1 рџ”ґ\nBoth goals blocked by missing Apollo lead gen agent\n\nрџ—“пёЏ TODAY'S AGENTS\n- вњ… 07:00 Workout Alert (fired)\n- вњ… 08:30 Daily Briefing (this one)\n- вЏі 21:00 Evening Debrief\n- вЏі 23:00 Daily Backup\n\nрџ’Ў ONE THING\nBuild the Apollo lead gen agent NOW. Pipedrive + Apollo keys both live. One conversation unblocks both Q1 goals.\n",
    "type": "daily",
    "createdAt": "2026-03-11T12:13:16.169Z"
  },
  {
    "id": "1773131476889",
    "title": "Daily Briefing вЂ” Tuesday 10 March 2026",
    "content": "рџ“° OpenClaw Daily Briefing вЂ” Tuesday, 10 March 2026\n\nв”Ђв”Ђв”Ђв”Ђв”Ђв”Ђв”Ђв”Ђв”Ђв”Ђв”Ђв”Ђв”Ђв”Ђв”Ђв”Ђв”Ђв”Ђв”Ђв”Ђв”Ђв”Ђв”Ђв”Ђв”Ђв”Ђв”Ђв”Ђв”Ђв”Ђв”Ђв”Ђв”Ђв”Ђв”Ђв”Ђв”Ђв”Ђв”Ђв”Ђв”Ђв”Ђв”Ђв”Ђв”Ђ\nвњ… LIVE & WORKING\nв”Ђв”Ђв”Ђв”Ђв”Ђв”Ђв”Ђв”Ђв”Ђв”Ђв”Ђв”Ђв”Ђв”Ђв”Ђв”Ђв”Ђв”Ђв”Ђв”Ђв”Ђв”Ђв”Ђв”Ђв”Ђв”Ђв”Ђв”Ђв”Ђв”Ђв”Ђв”Ђв”Ђв”Ђв”Ђв”Ђв”Ђв”Ђв”Ђв”Ђв”Ђв”Ђв”Ђв”Ђв”Ђ\nвЂў GoG / Gmail вЂ” read, send, calendar, drive, sheets, contacts\nвЂў Apollo API вЂ” lead search ready (key active)\nвЂў Pipedrive API вЂ” key in MEMORY.md, ready to connect\nвЂў Dashboard (Node.js) вЂ” live on port 3737, healthy\nвЂў Cloudflare Tunnel вЂ” permanent tunnel running\nвЂў 7AM Workout Email вЂ” cron b3ab2687 firing daily\nвЂў 8:30AM Daily Briefing вЂ” cron 3a8f30dc firing daily (this one)\nвЂў 9PM Evening Debrief вЂ” cron 459c61db firing daily\nвЂў 11PM Daily Backup вЂ” cron d862f688 firing daily\nвЂў Shell / Exec access вЂ” full tool profile active\nвЂў Desktop Startup Script вЂ” StartOpenClaw.vbs on Windows desktop\nвЂў Readwise API вЂ” 130 highlights connected\nвЂў WhatsApp channel вЂ” connected (briefing delivered here)\n\nв”Ђв”Ђв”Ђв”Ђв”Ђв”Ђв”Ђв”Ђв”Ђв”Ђв”Ђв”Ђв”Ђв”Ђв”Ђв”Ђв”Ђв”Ђв”Ђв”Ђв”Ђв”Ђв”Ђв”Ђв”Ђв”Ђв”Ђв”Ђв”Ђв”Ђв”Ђв”Ђв”Ђв”Ђв”Ђв”Ђв”Ђв”Ђв”Ђв”Ђв”Ђв”Ђв”Ђв”Ђв”Ђ\nрџ”„ IN PROGRESS\nв”Ђв”Ђв”Ђв”Ђв”Ђв”Ђв”Ђв”Ђв”Ђв”Ђв”Ђв”Ђв”Ђв”Ђв”Ђв”Ђв”Ђв”Ђв”Ђв”Ђв”Ђв”Ђв”Ђв”Ђв”Ђв”Ђв”Ђв”Ђв”Ђв”Ђв”Ђв”Ђв”Ђв”Ђв”Ђв”Ђв”Ђв”Ђв”Ђв”Ђв”Ђв”Ђв”Ђв”Ђв”Ђ\nвЂў Apollo lead gen agent (9AM cron) вЂ” structure ready, awaiting Pipedrive connection to close the loop\nвЂў Recipe agent (7:30AM) вЂ” approved, building\nвЂў Readwise knowledge graph вЂ” approved, building\nвЂў Readwise ICP-ranked daily email вЂ” approved, building\nвЂў Anam/Tavus social monitor вЂ” approved, building\nвЂў Community tracker (Reddit + HN + Brave в†’ Sheets) вЂ” approved, needs Google Sheet ID\nвЂў Meta-agent (10AM) вЂ” approved, not yet built\nвЂў Open questions agent (11AM) вЂ” approved, not yet built\nвЂў Job application agent вЂ” approved, needs final CV/Gmail wiring\nвЂў SQLite backend migration for dashboard вЂ” approved, not yet built\n\nв”Ђв”Ђв”Ђв”Ђв”Ђв”Ђв”Ђв”Ђв”Ђв”Ђв”Ђв”Ђв”Ђв”Ђв”Ђв”Ђв”Ђв”Ђв”Ђв”Ђв”Ђв”Ђв”Ђв”Ђв”Ђв”Ђв”Ђв”Ђв”Ђв”Ђв”Ђв”Ђв”Ђв”Ђв”Ђв”Ђв”Ђв”Ђв”Ђв”Ђв”Ђв”Ђв”Ђв”Ђв”Ђ\nвЏі PENDING YOUR ACTION\nв”Ђв”Ђв”Ђв”Ђв”Ђв”Ђв”Ђв”Ђв”Ђв”Ђв”Ђв”Ђв”Ђв”Ђв”Ђв”Ђв”Ђв”Ђв”Ђв”Ђв”Ђв”Ђв”Ђв”Ђв”Ђв”Ђв”Ђв”Ђв”Ђв”Ђв”Ђв”Ђв”Ђв”Ђв”Ђв”Ђв”Ђв”Ђв”Ђв”Ђв”Ђв”Ђв”Ђв”Ђв”Ђ\nвЂў DNS: Point nthlayerbot.co.uk nameservers to Cloudflare at your registrar вЂ” dashboard.nthlayerbot.co.uk will then resolve publicly\nвЂў Brave Search API key: Get at https://api.search.brave.com вЂ” unlocks community tracker + web search\nвЂў Google Sheet: Create a Sheet and share the ID вЂ” unlocks community tracker\nвЂў Podcast list: Share your podcast URLs вЂ” unlocks Whisper transcription agent\nвЂў Slack token: Share to enable Slack integration\nвЂў SoundCloud username: Share to enable SoundCloud integration\nвЂў Granola: Access/API details when available\n\nв”Ђв”Ђв”Ђв”Ђв”Ђв”Ђв”Ђв”Ђв”Ђв”Ђв”Ђв”Ђв”Ђв”Ђв”Ђв”Ђв”Ђв”Ђв”Ђв”Ђв”Ђв”Ђв”Ђв”Ђв”Ђв”Ђв”Ђв”Ђв”Ђв”Ђв”Ђв”Ђв”Ђв”Ђв”Ђв”Ђв”Ђв”Ђв”Ђв”Ђв”Ђв”Ђв”Ђв”Ђв”Ђ\nрџ”’ BLOCKED\nв”Ђв”Ђв”Ђв”Ђв”Ђв”Ђв”Ђв”Ђв”Ђв”Ђв”Ђв”Ђв”Ђв”Ђв”Ђв”Ђв”Ђв”Ђв”Ђв”Ђв”Ђв”Ђв”Ђв”Ђв”Ђв”Ђв”Ђв”Ђв”Ђв”Ђв”Ђв”Ђв”Ђв”Ђв”Ђв”Ђв”Ђв”Ђв”Ђв”Ђв”Ђв”Ђв”Ђв”Ђв”Ђ\nвЂў LinkedIn browser automation\n  FIX: Run `wsl --shutdown` in Windows PowerShell в†’ reopen WSL в†’ test with `curl -s http://localhost:9222`\n  Root cause: WSL2 mirrored networking doesn't expose localhost:9222 correctly until reset\n\nв”Ђв”Ђв”Ђв”Ђв”Ђв”Ђв”Ђв”Ђв”Ђв”Ђв”Ђв”Ђв”Ђв”Ђв”Ђв”Ђв”Ђв”Ђв”Ђв”Ђв”Ђв”Ђв”Ђв”Ђв”Ђв”Ђв”Ђв”Ђв”Ђв”Ђв”Ђв”Ђв”Ђв”Ђв”Ђв”Ђв”Ђв”Ђв”Ђв”Ђв”Ђв”Ђв”Ђв”Ђв”Ђ\nрџ“€ GOAL PROGRESS вЂ” Q1 2026\nв”Ђв”Ђв”Ђв”Ђв”Ђв”Ђв”Ђв”Ђв”Ђв”Ђв”Ђв”Ђв”Ђв”Ђв”Ђв”Ђв”Ђв”Ђв”Ђв”Ђв”Ђв”Ђв”Ђв”Ђв”Ђв”Ђв”Ђв”Ђв”Ђв”Ђв”Ђв”Ђв”Ђв”Ђв”Ђв”Ђв”Ђв”Ђв”Ђв”Ђв”Ђв”Ђв”Ђв”Ђв”Ђ\nвЂў Sonesse hot leads: 0 / 10 вЂ” Apollo connected but lead gen agent not yet running. Next step: activate 9AM agent once Pipedrive link confirmed.\nвЂў Nth Layer deal: Pipeline not yet in Pipedrive вЂ” but Pipedrive key is now in MEMORY.md. Next step: wire the Apollo в†’ Pipedrive agent and start logging prospects.\n\nв”Ђв”Ђв”Ђв”Ђв”Ђв”Ђв”Ђв”Ђв”Ђв”Ђв”Ђв”Ђв”Ђв”Ђв”Ђв”Ђв”Ђв”Ђв”Ђв”Ђв”Ђв”Ђв”Ђв”Ђв”Ђв”Ђв”Ђв”Ђв”Ђв”Ђв”Ђв”Ђв”Ђв”Ђв”Ђв”Ђв”Ђв”Ђв”Ђв”Ђв”Ђв”Ђв”Ђв”Ђв”Ђ\nрџ—“пёЏ TODAY'S AGENTS вЂ” Tuesday 10 March\nв”Ђв”Ђв”Ђв”Ђв”Ђв”Ђв”Ђв”Ђв”Ђв”Ђв”Ђв”Ђв”Ђв”Ђв”Ђв”Ђв”Ђв”Ђв”Ђв”Ђв”Ђв”Ђв”Ђв”Ђв”Ђв”Ђв”Ђв”Ђв”Ђв”Ђв”Ђв”Ђв”Ђв”Ђв”Ђв”Ђв”Ђв”Ђв”Ђв”Ђв”Ђв”Ђв”Ђв”Ђв”Ђ\nвЂў 07:00 вЂ” Workout email (live вњ…)\nвЂў 08:30 вЂ” This briefing (live вњ…)\nвЂў 21:00 вЂ” Evening debrief (live вњ…)\nвЂў 23:00 вЂ” Daily backup (live вњ…)\nвЂў Heartbeat вЂ” Every ~30 min: dashboard keep-alive + WhatsApp failover check\n\nв”Ђв”Ђв”Ђв”Ђв”Ђв”Ђв”Ђв”Ђв”Ђв”Ђв”Ђв”Ђв”Ђв”Ђв”Ђв”Ђв”Ђв”Ђв”Ђв”Ђв”Ђв”Ђв”Ђв”Ђв”Ђв”Ђв”Ђв”Ђв”Ђв”Ђв”Ђв”Ђв”Ђв”Ђв”Ђв”Ђв”Ђв”Ђв”Ђв”Ђв”Ђв”Ђв”Ђв”Ђв”Ђ\nрџ’Ў ONE THING\nв”Ђв”Ђв”Ђв”Ђв”Ђв”Ђв”Ђв”Ђв”Ђв”Ђв”Ђв”Ђв”Ђв”Ђв”Ђв”Ђв”Ђв”Ђв”Ђв”Ђв”Ђв”Ђв”Ђв”Ђв”Ђв”Ђв”Ђв”Ђв”Ђв”Ђв”Ђв”Ђв”Ђв”Ђв”Ђв”Ђв”Ђв”Ђв”Ђв”Ђв”Ђв”Ђв”Ђв”Ђв”Ђ\nRun `wsl --shutdown` in PowerShell right now. It takes 10 seconds and unblocks LinkedIn automation вЂ” the highest-leverage lead gen tool in your stack. Everything else is waiting on external keys. This one is entirely in your hands.\n\nв”Ђв”Ђв”Ђв”Ђв”Ђв”Ђв”Ђв”Ђв”Ђв”Ђв”Ђв”Ђв”Ђв”Ђв”Ђв”Ђв”Ђв”Ђв”Ђв”Ђв”Ђв”Ђв”Ђв”Ђв”Ђв”Ђв”Ђв”Ђв”Ђв”Ђв”Ђв”Ђв”Ђв”Ђв”Ђв”Ђв”Ђв”Ђв”Ђв”Ђв”Ђв”Ђв”Ђв”Ђв”Ђ\nGenerated by OpenClaw | 08:30 UTC | Cron: 3a8f30dc\n",
    "type": "daily",
    "createdAt": "2026-03-10T08:31:16.889Z"
  },
  {
    "id": "1772958709888",
    "title": "Daily Briefing вЂ” 8 March 2026",
    "content": "рџ“° OpenClaw Daily Briefing вЂ” Sunday, 8 March 2026\n\nв•ђв•ђв•ђв•ђв•ђв•ђв•ђв•ђв•ђв•ђв•ђв•ђв•ђв•ђв•ђв•ђв•ђв•ђв•ђв•ђв•ђв•ђв•ђв•ђв•ђв•ђв•ђв•ђв•ђв•ђв•ђв•ђв•ђв•ђв•ђв•ђв•ђв•ђв•ђв•ђв•ђв•ђв•ђв•ђв•ђв•ђв•ђв•ђ\nвњ… LIVE & WORKING\nв•ђв•ђв•ђв•ђв•ђв•ђв•ђв•ђв•ђв•ђв•ђв•ђв•ђв•ђв•ђв•ђв•ђв•ђв•ђв•ђв•ђв•ђв•ђв•ђв•ђв•ђв•ђв•ђв•ђв•ђв•ђв•ђв•ђв•ђв•ђв•ђв•ђв•ђв•ђв•ђв•ђв•ђв•ђв•ђв•ђв•ђв•ђв•ђ\n\nвЂў GoG / Gmail вЂ” connected, read/send/calendar/sheets all operational\nвЂў Apollo API вЂ” connected (key live, enrichment ready)\nвЂў Pipedrive API вЂ” connected (key confirmed live as of yesterday)\nвЂў Dashboard вЂ” running at localhost:3737, SQLite backend, login working\nвЂў Cloudflare tunnel вЂ” running (nthlayerbot.co.uk + nthlayer.co.uk configured)\nвЂў WhatsApp channel вЂ” operational\nвЂў Telegram bot вЂ” live (awaiting first pairing approval from Matthew)\nвЂў Chrome Browser Relay вЂ” working (LinkedIn messaging confirmed live)\nвЂў Homebrew (WSL) вЂ” installed\nвЂў Whisper (voice transcription) вЂ” installed, small model ready\nвЂў Google Sheets API вЂ” Job Tracker sheet live (63 jobs parsed, 27 logged yesterday)\nвЂў Crons (5 active):\n  в†’ 07:00 AM вЂ” Workout Alert вњ…\n  в†’ 08:00 AM вЂ” Daily Job Agent вњ… (27 leadership roles logged yesterday)\n  в†’ 08:30 AM вЂ” Daily Briefing вњ… (this one)\n  в†’ 09:00 PM вЂ” Evening Debrief вњ…\n  в†’ 11:00 PM вЂ” Daily Backup вњ…\n\nв•ђв•ђв•ђв•ђв•ђв•ђв•ђв•ђв•ђв•ђв•ђв•ђв•ђв•ђв•ђв•ђв•ђв•ђв•ђв•ђв•ђв•ђв•ђв•ђв•ђв•ђв•ђв•ђв•ђв•ђв•ђв•ђв•ђв•ђв•ђв•ђв•ђв•ђв•ђв•ђв•ђв•ђв•ђв•ђв•ђв•ђв•ђв•ђ\nрџ”„ IN PROGRESS\nв•ђв•ђв•ђв•ђв•ђв•ђв•ђв•ђв•ђв•ђв•ђв•ђв•ђв•ђв•ђв•ђв•ђв•ђв•ђв•ђв•ђв•ђв•ђв•ђв•ђв•ђв•ђв•ђв•ђв•ђв•ђв•ђв•ђв•ђв•ђв•ђв•ђв•ђв•ђв•ђв•ђв•ђв•ђв•ђв•ђв•ђв•ђв•ђ\n\nвЂў Apollo в†’ Pipedrive lead gen agent вЂ” Pipedrive now connected, ready to build (unblocked)\nвЂў Dashboard public URL вЂ” missioncontrol.nthlayer.co.uk has Error 1016 (cloudflared re-auth needed)\nвЂў IDENTITY.md вЂ” AI persona not yet named/configured\nвЂў Podcast transcription agent вЂ” planned, waiting on podcast list from Matthew\nвЂў Readwise knowledge graph вЂ” approved, not yet built\nвЂў Job application auto-filler вЂ” agent built, filtering working, application submission not yet automated\nвЂў nthlayer.co.uk вЂ” added to Cloudflare, WordPress at root (live)\n\nв•ђв•ђв•ђв•ђв•ђв•ђв•ђв•ђв•ђв•ђв•ђв•ђв•ђв•ђв•ђв•ђв•ђв•ђв•ђв•ђв•ђв•ђв•ђв•ђв•ђв•ђв•ђв•ђв•ђв•ђв•ђв•ђв•ђв•ђв•ђв•ђв•ђв•ђв•ђв•ђв•ђв•ђв•ђв•ђв•ђв•ђв•ђв•ђ\nвЏі PENDING YOUR ACTION\nв•ђв•ђв•ђв•ђв•ђв•ђв•ђв•ђв•ђв•ђв•ђв•ђв•ђв•ђв•ђв•ђв•ђв•ђв•ђв•ђв•ђв•ђв•ђв•ђв•ђв•ђв•ђв•ђв•ђв•ђв•ђв•ђв•ђв•ђв•ђв•ђв•ђв•ђв•ђв•ђв•ђв•ђв•ђв•ђв•ђв•ђв•ђв•ђ\n\n1. Brave Search API key вЂ” needed for research/signal agents\n   Sign up: https://api.search.brave.com\n   (Free tier available вЂ” takes 2 mins)\n\n2. Cloudflare re-auth for missioncontrol.nthlayer.co.uk\n   Run in WSL: /home/linuxbrew/.linuxbrew/bin/cloudflared tunnel login\n   Then authorise nthlayer.co.uk in the browser popup\n\n3. WSL shutdown вЂ” run once in Windows PowerShell:\n   wsl --shutdown\n   (Fixes LinkedIn automation вЂ” 10 seconds, huge unlock)\n\n4. Google Drive API вЂ” enable at:\n   https://console.developers.google.com (project ef901e5d)\n\n5. Podcast list вЂ” share URLs/show names for the transcription agent\n\n6. Telegram pairing вЂ” when you first message the Telegram bot, approve via:\n   openclaw pairing approve telegram <CODE>\n\nв•ђв•ђв•ђв•ђв•ђв•ђв•ђв•ђв•ђв•ђв•ђв•ђв•ђв•ђв•ђв•ђв•ђв•ђв•ђв•ђв•ђв•ђв•ђв•ђв•ђв•ђв•ђв•ђв•ђв•ђв•ђв•ђв•ђв•ђв•ђв•ђв•ђв•ђв•ђв•ђв•ђв•ђв•ђв•ђв•ђв•ђв•ђв•ђ\nрџ”’ BLOCKED\nв•ђв•ђв•ђв•ђв•ђв•ђв•ђв•ђв•ђв•ђв•ђв•ђв•ђв•ђв•ђв•ђв•ђв•ђв•ђв•ђв•ђв•ђв•ђв•ђв•ђв•ђв•ђв•ђв•ђв•ђв•ђв•ђв•ђв•ђв•ђв•ђв•ђв•ђв•ђв•ђв•ђв•ђв•ђв•ђв•ђв•ђв•ђв•ђ\n\n1. LinkedIn browser automation\n   Cause: WSL mirrored networking breaks CDP port forwarding\n   Fix: Run wsl --shutdown in Windows PowerShell, restart OpenClaw\n   Impact: Blocks Sonesse lead gen + Nth Layer ICP prospecting\n\n2. Dashboard public URL (missioncontrol.nthlayer.co.uk)\n   Cause: cloudflared cert expired during domain migration\n   Fix: cloudflared tunnel login (WSL) and authorise nthlayer.co.uk\n   Impact: Dashboard only accessible locally\n\n3. Brave Search / Signal agents\n   Cause: No API key\n   Fix: 2-minute signup at api.search.brave.com (free tier)\n   Impact: Blocks community monitoring, news-based prospect triggers\n\n4. Google Drive integration\n   Cause: Drive API not yet enabled in GCP console\n   Fix: Enable at console.developers.google.com\n   Impact: Blocks Drive file reading/writing via GoG\n\nв•ђв•ђв•ђв•ђв•ђв•ђв•ђв•ђв•ђв•ђв•ђв•ђв•ђв•ђв•ђв•ђв•ђв•ђв•ђв•ђв•ђв•ђв•ђв•ђв•ђв•ђв•ђв•ђв•ђв•ђв•ђв•ђв•ђв•ђв•ђв•ђв•ђв•ђв•ђв•ђв•ђв•ђв•ђв•ђв•ђв•ђв•ђв•ђ\nрџ“€ GOAL PROGRESS\nв•ђв•ђв•ђв•ђв•ђв•ђв•ђв•ђв•ђв•ђв•ђв•ђв•ђв•ђв•ђв•ђв•ђв•ђв•ђв•ђв•ђв•ђв•ђв•ђв•ђв•ђв•ђв•ђв•ђв•ђв•ђв•ђв•ђв•ђв•ђв•ђв•ђв•ђв•ђв•ђв•ђв•ђв•ђв•ђв•ђв•ђв•ђв•ђ\n\nQ1 Goal: 10 Sonesse hot leads\nв†’ Current: 0 / 10\nв†’ Apollo + Pipedrive both connected\nв†’ Lead gen agent NOT YET BUILT (can be done today once WSL fixed)\nв†’ Target: CTOs / VP Eng / Head of AI at companies deploying conversational AI\n\nQ1 Goal: 1 Nth Layer deal closed\nв†’ Current: 0 / 1\nв†’ Outreach infra ready; LinkedIn automation still blocked (WSL fix)\nв†’ Job agent running as parallel cashflow bridge (27 leadership roles logged yesterday)\nв†’ Next lever: build Apollo в†’ Pipedrive pipeline agent\n\nв•ђв•ђв•ђв•ђв•ђв•ђв•ђв•ђв•ђв•ђв•ђв•ђв•ђв•ђв•ђв•ђв•ђв•ђв•ђв•ђв•ђв•ђв•ђв•ђв•ђв•ђв•ђв•ђв•ђв•ђв•ђв•ђв•ђв•ђв•ђв•ђв•ђв•ђв•ђв•ђв•ђв•ђв•ђв•ђв•ђв•ђв•ђв•ђ\nрџ—“пёЏ TODAY'S AGENTS вЂ” Sunday, 8 March\nв•ђв•ђв•ђв•ђв•ђв•ђв•ђв•ђв•ђв•ђв•ђв•ђв•ђв•ђв•ђв•ђв•ђв•ђв•ђв•ђв•ђв•ђв•ђв•ђв•ђв•ђв•ђв•ђв•ђв•ђв•ђв•ђв•ђв•ђв•ђв•ђв•ђв•ђв•ђв•ђв•ђв•ђв•ђв•ђв•ђв•ђв•ђв•ђ\n\nвњ… 07:00 вЂ” Workout Alert (fired 90 mins ago)\nвњ… 08:30 вЂ” This briefing (running now)\nвЏі 21:00 вЂ” Evening Debrief (in ~12.5h)\nвЏі 23:00 вЂ” Daily Backup (in ~14.5h)\n\nNote: Job Agent (08:00) runs MondayвЂ“Friday only.\n\nв•ђв•ђв•ђв•ђв•ђв•ђв•ђв•ђв•ђв•ђв•ђв•ђв•ђв•ђв•ђв•ђв•ђв•ђв•ђв•ђв•ђв•ђв•ђв•ђв•ђв•ђв•ђв•ђв•ђв•ђв•ђв•ђв•ђв•ђв•ђв•ђв•ђв•ђв•ђв•ђв•ђв•ђв•ђв•ђв•ђв•ђв•ђв•ђ\nрџ’Ў ONE THING\nв•ђв•ђв•ђв•ђв•ђв•ђв•ђв•ђв•ђв•ђв•ђв•ђв•ђв•ђв•ђв•ђв•ђв•ђв•ђв•ђв•ђв•ђв•ђв•ђв•ђв•ђв•ђв•ђв•ђв•ђв•ђв•ђв•ђв•ђв•ђв•ђв•ђв•ђв•ђв•ђв•ђв•ђв•ђв•ђв•ђв•ђв•ђв•ђ\n\nRun wsl --shutdown in Windows PowerShell. Right now.\n\nIt's 10 seconds. It fixes LinkedIn automation. LinkedIn automation\nunlocks both Sonesse lead gen AND Nth Layer prospecting вЂ” everything\nelse is already built and waiting. This is the single point of failure\nbetween where you are and automated pipeline growth.\n\nOpen PowerShell в†’ type: wsl --shutdown в†’ hit Enter в†’ reply here.\nI'll start outreach immediately.\n\nв•ђв•ђв•ђв•ђв•ђв•ђв•ђв•ђв•ђв•ђв•ђв•ђв•ђв•ђв•ђв•ђв•ђв•ђв•ђв•ђв•ђв•ђв•ђв•ђв•ђв•ђв•ђв•ђв•ђв•ђв•ђв•ђв•ђв•ђв•ђв•ђв•ђв•ђв•ђв•ђв•ђв•ђв•ђв•ђв•ђв•ђв•ђв•ђ\n",
    "type": "daily",
    "createdAt": "2026-03-08T08:31:49.888Z"
  },
  {
    "id": "1772872360002",
    "title": "Daily Briefing - 7 March 2026",
    "content": "рџ“° OpenClaw Daily Briefing вЂ” Saturday, 7 March 2026\n\nв•ђв•ђв•ђв•ђв•ђв•ђв•ђв•ђв•ђв•ђв•ђв•ђв•ђв•ђв•ђв•ђв•ђв•ђв•ђв•ђв•ђв•ђв•ђв•ђв•ђв•ђв•ђв•ђв•ђв•ђв•ђв•ђв•ђв•ђв•ђв•ђв•ђв•ђв•ђв•ђв•ђв•ђв•ђв•ђв•ђв•ђв•ђв•ђ\nвњ… LIVE & WORKING\nв•ђв•ђв•ђв•ђв•ђв•ђв•ђв•ђв•ђв•ђв•ђв•ђв•ђв•ђв•ђв•ђв•ђв•ђв•ђв•ђв•ђв•ђв•ђв•ђв•ђв•ђв•ђв•ђв•ђв•ђв•ђв•ђв•ђв•ђв•ђв•ђв•ђв•ђв•ђв•ђв•ђв•ђв•ђв•ђв•ђв•ђв•ђв•ђ\n\n- GoG / Gmail: connected and operational\n- Apollo API: connected (enrichment ready)\n- Pipedrive API: connected (key live as of yesterday)\n- Dashboard: localhost:3737 live with SQLite backend, login working\n- Cloudflare tunnel: running (nthlayerbot.co.uk + nthlayer.co.uk configured)\n- WhatsApp channel: operational\n- Telegram bot: set up and running\n- Chrome Browser Relay: working (LinkedIn messaging confirmed live вЂ” sent 2 test messages 05-Mar)\n- Homebrew (WSL): installed\n- Whisper (voice transcription): installed, small model ready\n- Google Sheets API: enabled вЂ” Job Tracker sheet live\n- Cron jobs: 5 active\n  вЂў 7:00 AM  вЂ” Workout Alert вњ…\n  вЂў 8:00 AM  вЂ” Daily Job Agent вњ… (ran 30min ago вЂ” 27 jobs logged)\n  вЂў 8:30 AM  вЂ” Daily Briefing вњ… (you're reading it)\n  вЂў 9:00 PM  вЂ” Daily Debrief вњ…\n  вЂў 11:00 PM вЂ” Daily Backup вњ…\n\nв•ђв•ђв•ђв•ђв•ђв•ђв•ђв•ђв•ђв•ђв•ђв•ђв•ђв•ђв•ђв•ђв•ђв•ђв•ђв•ђв•ђв•ђв•ђв•ђв•ђв•ђв•ђв•ђв•ђв•ђв•ђв•ђв•ђв•ђв•ђв•ђв•ђв•ђв•ђв•ђв•ђв•ђв•ђв•ђв•ђв•ђв•ђв•ђ\nрџ”„ IN PROGRESS\nв•ђв•ђв•ђв•ђв•ђв•ђв•ђв•ђв•ђв•ђв•ђв•ђв•ђв•ђв•ђв•ђв•ђв•ђв•ђв•ђв•ђв•ђв•ђв•ђв•ђв•ђв•ђв•ђв•ђв•ђв•ђв•ђв•ђв•ђв•ђв•ђв•ђв•ђв•ђв•ђв•ђв•ђв•ђв•ђв•ђв•ђв•ђв•ђ\n\n- Apollo lead gen agent: Pipedrive now connected вЂ” ready to build the pipeline agent\n- Dashboard public URL: configured for missioncontrol.nthlayer.co.uk (Error 1016 вЂ” pending cloudflared re-auth)\n- IDENTITY.md: blank вЂ” AI persona not yet named/configured\n- Podcast transcription agent: planned, waiting on podcast list from Matthew\n\nв•ђв•ђв•ђв•ђв•ђв•ђв•ђв•ђв•ђв•ђв•ђв•ђв•ђв•ђв•ђв•ђв•ђв•ђв•ђв•ђв•ђв•ђв•ђв•ђв•ђв•ђв•ђв•ђв•ђв•ђв•ђв•ђв•ђв•ђв•ђв•ђв•ђв•ђв•ђв•ђв•ђв•ђв•ђв•ђв•ђв•ђв•ђв•ђ\nвЏі PENDING YOUR ACTION\nв•ђв•ђв•ђв•ђв•ђв•ђв•ђв•ђв•ђв•ђв•ђв•ђв•ђв•ђв•ђв•ђв•ђв•ђв•ђв•ђв•ђв•ђв•ђв•ђв•ђв•ђв•ђв•ђв•ђв•ђв•ђв•ђв•ђв•ђв•ђв•ђв•ђв•ђв•ђв•ђв•ђв•ђв•ђв•ђв•ђв•ђв•ђв•ђ\n\n1. Brave Search API key вЂ” needed for research/news agents (sign up at brave.com/search/api)\n2. Cloudflare re-auth вЂ” run this in WSL to fix dashboard public URL:\n   /home/linuxbrew/.linuxbrew/bin/cloudflared tunnel login\n   (then authorise nthlayer.co.uk in the browser)\n3. Google Drive API вЂ” enable at: console.developers.google.com (project ef901e5d)\n4. Slack token вЂ” for Slack integration (if still wanted)\n5. Podcast list вЂ” URLs/shows for the transcription agent\n6. WSL shutdown fix вЂ” run in Windows PowerShell:\n   wsl --shutdown\n   (then restart WSL вЂ” this fixes LinkedIn browser automation)\n\nв•ђв•ђв•ђв•ђв•ђв•ђв•ђв•ђв•ђв•ђв•ђв•ђв•ђв•ђв•ђв•ђв•ђв•ђв•ђв•ђв•ђв•ђв•ђв•ђв•ђв•ђв•ђв•ђв•ђв•ђв•ђв•ђв•ђв•ђв•ђв•ђв•ђв•ђв•ђв•ђв•ђв•ђв•ђв•ђв•ђв•ђв•ђв•ђ\nрџ”’ BLOCKED\nв•ђв•ђв•ђв•ђв•ђв•ђв•ђв•ђв•ђв•ђв•ђв•ђв•ђв•ђв•ђв•ђв•ђв•ђв•ђв•ђв•ђв•ђв•ђв•ђв•ђв•ђв•ђв•ђв•ђв•ђв•ђв•ђв•ђв•ђв•ђв•ђв•ђв•ђв•ђв•ђв•ђв•ђв•ђв•ђв•ђв•ђв•ђв•ђ\n\n1. LinkedIn browser automation\n   - Cause: WSL mirrored networking breaks CDP port forwarding\n   - Fix: Run `wsl --shutdown` in Windows PowerShell, then restart OpenClaw gateway\n   - Impact: Blocks Sonesse lead gen, Nth Layer prospecting\n\n2. Dashboard public URL (missioncontrol.nthlayer.co.uk)\n   - Cause: cloudflared cert expired/removed during domain migration\n   - Fix: Run `cloudflared tunnel login` in WSL and authorise nthlayer.co.uk\n   - Impact: Dashboard only accessible on local network\n\n3. Brave Search research agent\n   - Cause: No API key\n   - Fix: Sign up at brave.com/search/api (free tier available)\n   - Impact: Blocks signal-based prospecting and news monitoring agents\n\nв•ђв•ђв•ђв•ђв•ђв•ђв•ђв•ђв•ђв•ђв•ђв•ђв•ђв•ђв•ђв•ђв•ђв•ђв•ђв•ђв•ђв•ђв•ђв•ђв•ђв•ђв•ђв•ђв•ђв•ђв•ђв•ђв•ђв•ђв•ђв•ђв•ђв•ђв•ђв•ђв•ђв•ђв•ђв•ђв•ђв•ђв•ђв•ђ\nрџ“€ GOAL PROGRESS\nв•ђв•ђв•ђв•ђв•ђв•ђв•ђв•ђв•ђв•ђв•ђв•ђв•ђв•ђв•ђв•ђв•ђв•ђв•ђв•ђв•ђв•ђв•ђв•ђв•ђв•ђв•ђв•ђв•ђв•ђв•ђв•ђв•ђв•ђв•ђв•ђв•ђв•ђв•ђв•ђв•ђв•ђв•ђв•ђв•ђв•ђв•ђв•ђ\n\nQ1 Goal: 10 Sonesse hot leads\nв†’ Current: 0 / 10\nв†’ Status: Apollo + Pipedrive connected, but lead gen agent not yet built\nв†’ Next step: Build Apollo в†’ Pipedrive pipeline agent (unblocked вЂ” can do today)\n\nQ1 Goal: 1 Nth Layer deal closed\nв†’ Current: 0 / 1\nв†’ Status: Outreach infrastructure ready; LinkedIn automation blocked (WSL fix needed)\nв†’ Job agent running (parallel income bridge вЂ” 27 leads logged this morning)\n\nв•ђв•ђв•ђв•ђв•ђв•ђв•ђв•ђв•ђв•ђв•ђв•ђв•ђв•ђв•ђв•ђв•ђв•ђв•ђв•ђв•ђв•ђв•ђв•ђв•ђв•ђв•ђв•ђв•ђв•ђв•ђв•ђв•ђв•ђв•ђв•ђв•ђв•ђв•ђв•ђв•ђв•ђв•ђв•ђв•ђв•ђв•ђв•ђ\nрџ—“пёЏ TODAY'S AGENTS (Saturday, 7 March)\nв•ђв•ђв•ђв•ђв•ђв•ђв•ђв•ђв•ђв•ђв•ђв•ђв•ђв•ђв•ђв•ђв•ђв•ђв•ђв•ђв•ђв•ђв•ђв•ђв•ђв•ђв•ђв•ђв•ђв•ђв•ђв•ђв•ђв•ђв•ђв•ђв•ђв•ђв•ђв•ђв•ђв•ђв•ђв•ђв•ђв•ђв•ђв•ђ\n\nвњ… 07:00 вЂ” Workout Alert (fired 2h ago)\nвњ… 08:00 вЂ” Daily Job Agent (ran вЂ” 27 leadership roles logged to sheet)\nвњ… 08:30 вЂ” Daily Briefing (this one, running now)\nвЏі 21:00 вЂ” Daily Debrief (in ~12h)\nвЏі 23:00 вЂ” Daily Backup (in ~14h)\n\nв•ђв•ђв•ђв•ђв•ђв•ђв•ђв•ђв•ђв•ђв•ђв•ђв•ђв•ђв•ђв•ђв•ђв•ђв•ђв•ђв•ђв•ђв•ђв•ђв•ђв•ђв•ђв•ђв•ђв•ђв•ђв•ђв•ђв•ђв•ђв•ђв•ђв•ђв•ђв•ђв•ђв•ђв•ђв•ђв•ђв•ђв•ђв•ђ\nрџ’Ў ONE THING\nв•ђв•ђв•ђв•ђв•ђв•ђв•ђв•ђв•ђв•ђв•ђв•ђв•ђв•ђв•ђв•ђв•ђв•ђв•ђв•ђв•ђв•ђв•ђв•ђв•ђв•ђв•ђв•ђв•ђв•ђв•ђв•ђв•ђв•ђв•ђв•ђв•ђв•ђв•ђв•ђв•ђв•ђв•ђв•ђв•ђв•ђв•ђв•ђ\n\nRun `wsl --shutdown` in Windows PowerShell right now.\n\nIt takes 10 seconds. It fixes LinkedIn browser automation. LinkedIn automation is\nthe lever that drives both Sonesse leads AND Nth Layer prospecting вЂ” everything\nelse is plumbing that's already done. This is the unlock.\n\nAfter restart, reply here and I'll immediately begin automated LinkedIn outreach\nto your ICP.\n\nв•ђв•ђв•ђв•ђв•ђв•ђв•ђв•ђв•ђв•ђв•ђв•ђв•ђв•ђв•ђв•ђв•ђв•ђв•ђв•ђв•ђв•ђв•ђв•ђв•ђв•ђв•ђв•ђв•ђв•ђв•ђв•ђв•ђв•ђв•ђв•ђв•ђв•ђв•ђв•ђв•ђв•ђв•ђв•ђв•ђв•ђв•ђв•ђ\n",
    "type": "daily",
    "createdAt": "2026-03-07T08:32:40.002Z"
  },
  {
    "id": "1772750371956",
    "title": "рџ“° OpenClaw Setup Progress вЂ” Day 1",
    "content": "вњ… LIVE & WORKING\nвЂў Gmail / GoG вЂ” read, send, search, calendar, drive, sheets all connected\nвЂў Apollo API вЂ” authenticated and ready for lead searches\nвЂў Dashboard вЂ” running at 82ebc6e5-eeae-4532-8331-325d82345028.cfargotunnel.com\nвЂў Cloudflare Tunnel вЂ” named tunnel (matthew-dashboard) running permanently\nвЂў 7:00 AM Workout Email вЂ” live, sends 4 HYROX/strength/CrossFit workouts daily\nвЂў 8:30 AM Daily Briefing вЂ” live (this one!)\nвЂў 9:00 PM Evening Debrief вЂ” live\nвЂў 11:00 PM Daily Backup вЂ” live, saves to Documents/Backup\nвЂў GoG Keyring вЂ” configured with persistent password\nвЂў Shell/Exec access вЂ” enabled for autonomous operation\nвЂў Desktop Startup Script вЂ” on Windows desktop (StartOpenClaw.vbs)\nвЂў All 8 dashboard tabs built: Tasks, Agents, Systems, Memory, Goals, Meta Agent, ICPs, LinkedIn Posts, Briefings\n\nрџ”„ IN PROGRESS\nвЂў dashboard.nthlayerbot.co.uk вЂ” DNS record set in Cloudflare, waiting for domain nameservers to point to Cloudflare\nвЂў Recipe agent вЂ” plan approved, building tab + cron\nвЂў Podcast tab вЂ” plan approved, waiting on podcast list + SoundCloud username\nвЂў Community discussion tracker вЂ” plan approved, needs Google Sheet ID\nвЂў SQLite backend вЂ” plan approved, ready to build\nвЂў Job application agent вЂ” plan approved, needs CV + Gmail folder names\nвЂў High-signal lead gen agent вЂ” designed, ready to build\n\nвЏі PENDING YOUR ACTION\nвЂў Run wsl --shutdown in PowerShell (unlocks LinkedIn browser automation)\nвЂў Share Pipedrive API key\nвЂў Share Brave Search API key (from api.search.brave.com)\nвЂў Share Readwise API token (from readwise.io/access_token)\nвЂў Share SoundCloud username\nвЂў Share CV for job application agent\nвЂў Create Google Sheet for community tracker and share ID\nвЂў Update nthlayerbot.co.uk nameservers at registrar to Cloudflare\nвЂў Share remaining Q1 goals\n\nрџ”’ BLOCKED\nвЂў LinkedIn automation вЂ” needs WSL mirrored networking (fix: run wsl --shutdown in PowerShell, then reopen WSL)\nвЂў Web search вЂ” needs Brave API key\nвЂў Amanda Recall.ai LinkedIn scrape вЂ” needs browser working\n\nрџ“€ GOAL PROGRESS\nвЂў Sonesse hot leads: 0 / 10 (Apollo connected, lead gen agent not yet running)\nвЂў Nth Layer deal: 0 / 1 (no pipeline data yet вЂ” Pipedrive key needed)\n\nрџ—“пёЏ TODAY'S AGENTS\nвЂў 7:00 AM вЂ” Workout email вњ…\nвЂў 8:30 AM вЂ” This briefing вњ…\nвЂў 9:00 PM вЂ” Evening debrief\nвЂў 11:00 PM вЂ” Backup\n\nрџ’Ў ONE THING\nRun wsl --shutdown in Windows PowerShell right now. It takes 30 seconds and unlocks LinkedIn browser automation, which is the highest-value thing currently blocked.",
    "type": "daily",
    "createdAt": "2026-03-05T22:39:31.956Z"
  }
]